{
  "id": "EVID-2026-HW1-R06",
  "timestamp": "2026-04-26T11:37:23.589421+00:00",
  "source_type": "hardware_test",
  "domain": "backup_restore",
  "platform": "linux_laptop",
  "scenario": "HW1-01",
  "test_goal": "HW1-01 R06 End-to-End nach FIX-4 (Backup+Verify+Preview ohne sudo/ohne /opt im Data-Scope)",
  "outcome": "failed",
  "severity": "medium",
  "confidence": "high",
  "system_profile_id": "profile-linux-laptop-nvme-host",
  "storage_profile": "",
  "encryption_profile": "",
  "boot_profile": "",
  "observed_symptoms": [
    "Pre-Check fehlgeschlagen: test-run nicht als ext4 gemountet (findmnt ohne Treffer).",
    "Zielpfadrechte falsch: /mnt/setuphelfer/backups/test-run = root:root 0755 statt root:setuphelfer 0770.",
    "Schreibprobe fehlgeschlagen: touch _probe_r06 -> Keine Berechtigung.",
    "API-Version erreichbar: 1.5.0.0."
  ],
  "raw_signals": {
    "precheck": {
      "id_G": "1000 4 24 27 30 46 100 105 125 132 1001",
      "findmnt_test_run": "no_entry",
      "ls_ld_test_run": "drwxr-xr-x 2 root root 4096 Apr 24 22:43 /mnt/setuphelfer/backups/test-run",
      "touch_probe": "touch: '/mnt/setuphelfer/backups/test-run/_probe_r06' kann nicht berührt werden: Keine Berechtigung",
      "api_version": {
        "status": "success",
        "version": "1.5.0.0"
      }
    },
    "execution": {
      "backup_create_executed": false,
      "verify_executed": false,
      "restore_preview_executed": false,
      "abort_phase": "phase_0_precheck"
    }
  },
  "matched_diagnosis_ids": [
    "OWNER-MODE-023",
    "PERM-GROUP-008"
  ],
  "diagnosis_links": [
    "BACKUP-SOURCE-PERM-032"
  ],
  "suspected_root_causes": [
    "Mountpoint /mnt/setuphelfer/backups/test-run ist nicht im erwarteten ext4-Mountzustand.",
    "Owner/Mode des Zielpfads nicht HW1-konform, dadurch kein Schreibzugriff im Dienstkontext."
  ],
  "confirmed_root_cause": "Vorbedingung fuer R06 nicht erfuellt (kein ext4-Mount + falsche Rechte), daher Lauf vor Backup-Start abgebrochen.",
  "corrective_actions": [
    "ext4-Partition erneut auf /mnt/setuphelfer/backups/test-run mounten.",
    "Owner/Mode auf root:setuphelfer und 0770 (drwxrws---) setzen.",
    "Schreibprobe und findmnt erneut gruen pruefen, dann R06 neu starten."
  ],
  "unresolved_questions": [
    "Welche Partition ist aktuell der korrekte test-run-Datentraeger (z. B. /dev/sda4)?"
  ],
  "docs_updated": true,
  "faq_updated": false,
  "catalog_updated": false,
  "tests_added": false
}
