{
  "task": "BR-001-full-root-stable-retry",
  "captured_at": "2026-05-20T17:45:00Z",
  "head_before_start": "527dafa",
  "previous_failed_jobs": ["1f54bdd9ea2f", "2a15912d1b52"],
  "profile": "full-root-stable",
  "api_type": "profile",
  "runner_backup_type": "full",
  "package_freeze_active_before_start": true,
  "target_path": "/media/setuphelfer/br001",
  "target_device": "/dev/sda1",
  "target_fstype": "ext4",
  "target_is_usb": true,
  "runtime_gate_exit": 0,
  "smtp_last_test_status_before_start": "sent",
  "on_backup_failure": true,
  "partial_present_before_start": false,
  "package_activity_preflight": "ok",
  "backup_started": true,
  "job_id": "fb1a5edf350a",
  "backup_start_utc": "2026-05-20T16:57:24Z",
  "backup_finished_utc": "2026-05-20T17:37:11Z",
  "archive_planned": "/media/setuphelfer/br001/pi-backup-full-20260520_185724.tar.gz",
  "systemd_unit": "setuphelfer-backup@fb1a5edf350a.service",
  "status": "cancelled",
  "br001_status": "cancelled",
  "code": "backup.cancelled",
  "diagnosis_id": "BACKUP-CANCEL-001",
  "abort_reason": "user_cancel",
  "phase_final": "preflight",
  "compression_engine": "gzip",
  "compression_reason": "pigz_not_found_fallback_gzip",
  "written_bytes": 52045545472,
  "written_human": "48.47 GiB",
  "elapsed_seconds": 2385,
  "tar_return_code": null,
  "tar_warning_classification": null,
  "partial_deleted": true,
  "partial_present_after": false,
  "final_archive_exists": false,
  "final_archive_path": null,
  "final_archive_size_bytes": 0,
  "sha256_present": false,
  "sha256_verified": false,
  "sha256_skipped_reason": "no_final_archive",
  "verify_deep_started": false,
  "verify_deep_ok": false,
  "verify_deep_skipped_reason": "no_final_archive",
  "notification_status": "unknown",
  "failure_mail_expected": false,
  "failure_mail_note": "backup.cancelled is not a failure notification trigger",
  "package_activity_during_run": false,
  "mount_at_end": {
    "target": "/media/setuphelfer/br001",
    "source": "/dev/sda1",
    "fstype": "ext4"
  },
  "backend_active_at_end": true,
  "restore_started": false,
  "apt_update_run": false,
  "apt_upgrade_run": false,
  "apt_install_run": false,
  "apt_autoremove_run": false,
  "br001_result": "red",
  "br001_decision_reason": "Backup cancelled (user_cancel) after ~48 GiB; no final archive, no SHA256, no Verify Deep. Not tar_failed; investigate cancel source (SIGTERM/API) before retry."
}
